sqlalchemy_utils-stubs/METADATA.toml
sqlalchemy_utils-stubs/__init__.pyi
sqlalchemy_utils-stubs/aggregates.pyi
sqlalchemy_utils-stubs/asserts.pyi
sqlalchemy_utils-stubs/batch.pyi
sqlalchemy_utils-stubs/compat.pyi
sqlalchemy_utils-stubs/decorators.pyi
sqlalchemy_utils-stubs/exceptions.pyi
sqlalchemy_utils-stubs/expression_parser.pyi
sqlalchemy_utils-stubs/expressions.pyi
sqlalchemy_utils-stubs/generic.pyi
sqlalchemy_utils-stubs/i18n.pyi
sqlalchemy_utils-stubs/listeners.pyi
sqlalchemy_utils-stubs/models.pyi
sqlalchemy_utils-stubs/observer.pyi
sqlalchemy_utils-stubs/operators.pyi
sqlalchemy_utils-stubs/path.pyi
sqlalchemy_utils-stubs/proxy_dict.pyi
sqlalchemy_utils-stubs/query_chain.pyi
sqlalchemy_utils-stubs/utils.pyi
sqlalchemy_utils-stubs/view.pyi
sqlalchemy_utils-stubs/functions/__init__.pyi
sqlalchemy_utils-stubs/functions/database.pyi
sqlalchemy_utils-stubs/functions/defer_except.pyi
sqlalchemy_utils-stubs/functions/foreign_keys.pyi
sqlalchemy_utils-stubs/functions/mock.pyi
sqlalchemy_utils-stubs/functions/orm.pyi
sqlalchemy_utils-stubs/functions/render.pyi
sqlalchemy_utils-stubs/functions/sort_query.pyi
sqlalchemy_utils-stubs/primitives/__init__.pyi
sqlalchemy_utils-stubs/primitives/country.pyi
sqlalchemy_utils-stubs/primitives/currency.pyi
sqlalchemy_utils-stubs/primitives/ltree.pyi
sqlalchemy_utils-stubs/primitives/weekday.pyi
sqlalchemy_utils-stubs/primitives/weekdays.pyi
sqlalchemy_utils-stubs/relationships/__init__.pyi
sqlalchemy_utils-stubs/relationships/chained_join.pyi
sqlalchemy_utils-stubs/types/__init__.pyi
sqlalchemy_utils-stubs/types/arrow.pyi
sqlalchemy_utils-stubs/types/bit.pyi
sqlalchemy_utils-stubs/types/choice.pyi
sqlalchemy_utils-stubs/types/color.pyi
sqlalchemy_utils-stubs/types/country.pyi
sqlalchemy_utils-stubs/types/currency.pyi
sqlalchemy_utils-stubs/types/email.pyi
sqlalchemy_utils-stubs/types/ip_address.pyi
sqlalchemy_utils-stubs/types/json.pyi
sqlalchemy_utils-stubs/types/locale.pyi
sqlalchemy_utils-stubs/types/ltree.pyi
types_sqlalchemy_utils-1.1.0.dist-info/LICENSE
types_sqlalchemy_utils-1.1.0.dist-info/METADATA
types_sqlalchemy_utils-1.1.0.dist-info/WHEEL
types_sqlalchemy_utils-1.1.0.dist-info/top_level.txt
types_sqlalchemy_utils-1.1.0.dist-info/RECORD
